AUTHORS.md
CONTRIBUTING.md
LICENSE
MANIFEST.in
README.md
setup.py
modernremodel/__init__.py
modernremodel/connection.py
modernremodel/decorators.py
modernremodel/errors.py
modernremodel/field_handler.py
modernremodel/helpers.py
modernremodel/models.py
modernremodel/monkey.py
modernremodel/object_handler.py
modernremodel/registry.py
modernremodel/related.py
modernremodel/utils.py
modernremodel.egg-info/PKG-INFO
modernremodel.egg-info/SOURCES.txt
modernremodel.egg-info/dependency_links.txt
modernremodel.egg-info/not-zip-safe
modernremodel.egg-info/requires.txt
modernremodel.egg-info/top_level.txt
tests/__init__.py
tests/test_decorators.py
tests/test_field_handler.py
tests/test_helpers.py
tests/test_models.py
tests/test_object_handler.py
tests/test_registry.py
tests/test_related.py